aslabs/dependencies/fastapi/__init__.py
aslabs/dependencies/fastapi/fastapi.py
aslabs/dependencies/fastapi/resolvers.py
aslabs/py.typed
aslabs_dependencies_fastapi-0.0.9.dist-info/WHEEL
aslabs_dependencies_fastapi-0.0.9.dist-info/METADATA
aslabs_dependencies_fastapi-0.0.9.dist-info/RECORD
