Metadata-Version: 2.1
Name: aslabs-dependencies-fastapi
Version: 0.0.9
Summary: 
Author: Titusz Ban
Author-email: tituszban@antisociallabs.io
Requires-Python: >=3.9,<4.0
Classifier: Programming Language :: Python :: 3
Classifier: Programming Language :: Python :: 3.9
Classifier: Programming Language :: Python :: 3.10
Classifier: Programming Language :: Python :: 3.11
Requires-Dist: aslabs-dependencies
Requires-Dist: fastapi (>=0.86.0,<0.87.0)
